instapaper_scraper/__init__.py
instapaper_scraper/api.py
instapaper_scraper/auth.py
instapaper_scraper/cli.py
instapaper_scraper/constants.py
instapaper_scraper/exceptions.py
instapaper_scraper/output.py
instapaper_scraper-1.1.1.dist-info/licenses/LICENSE
instapaper_scraper-1.1.1.dist-info/METADATA
instapaper_scraper-1.1.1.dist-info/WHEEL
instapaper_scraper-1.1.1.dist-info/entry_points.txt
instapaper_scraper-1.1.1.dist-info/top_level.txt
instapaper_scraper-1.1.1.dist-info/RECORD
