Metadata-Version: 2.4
Name: instapaper-scraper
Version: 1.1.1
Summary: A tool to scrape articles from Instapaper.
Project-URL: Homepage, https://github.com/chriskyfung/InstapaperScraper
Project-URL: Source, https://github.com/chriskyfung/InstapaperScraper
Project-URL: Issues, https://github.com/chriskyfung/InstapaperScraper/issues
Classifier: Programming Language :: Python :: 3
Classifier: Programming Language :: Python :: 3.9
Classifier: Programming Language :: Python :: 3.10
Classifier: Programming Language :: Python :: 3.11
Classifier: Programming Language :: Python :: 3.12
Classifier: Programming Language :: Python :: 3.13
Classifier: Programming Language :: Python :: 3.14
Classifier: Development Status :: 5 - Production/Stable
Classifier: Intended Audience :: End Users/Desktop
Classifier: Topic :: Internet :: WWW/HTTP :: Browsers
Classifier: License :: OSI Approved :: GNU General Public License v3 (GPLv3)
Classifier: Operating System :: OS Independent
Requires-Python: >=3.9
License-File: LICENSE
Requires-Dist: beautifulsoup4~=4.14.2
Requires-Dist: certifi~=2025.11.12
Requires-Dist: charset-normalizer~=3.4.3
Requires-Dist: cryptography~=46.0.3
Requires-Dist: guara~=0.0.14
Requires-Dist: idna~=3.11
Requires-Dist: python-dotenv~=1.2.1
Requires-Dist: requests~=2.32.5
Requires-Dist: soupsieve~=2.8
Requires-Dist: typing_extensions~=4.15.0
Requires-Dist: urllib3<2.7,>=2.5
Requires-Dist: tomli~=2.0.1; python_version < "3.11"
Provides-Extra: dev
Requires-Dist: pytest; extra == "dev"
Requires-Dist: pytest-cov; extra == "dev"
Requires-Dist: ruff; extra == "dev"
Requires-Dist: types-requests; extra == "dev"
Requires-Dist: types-beautifulsoup4; extra == "dev"
Requires-Dist: requests-mock; extra == "dev"
Requires-Dist: build; extra == "dev"
Requires-Dist: twine; extra == "dev"
Requires-Dist: mypy; extra == "dev"
Requires-Dist: pre-commit; extra == "dev"
Requires-Dist: licensecheck; extra == "dev"
Dynamic: license-file
